mock_services/__init__.py
mock_services/decorators.py
mock_services/exceptions.py
mock_services/helpers.py
mock_services/http_mock.py
mock_services/rules.py
mock_services/service.py
mock_services/storage.py
mock_services-0.3.1.dist-info/DESCRIPTION.rst
mock_services-0.3.1.dist-info/METADATA
mock_services-0.3.1.dist-info/RECORD
mock_services-0.3.1.dist-info/WHEEL
mock_services-0.3.1.dist-info/metadata.json
mock_services-0.3.1.dist-info/top_level.txt
