Metadata-Version: 2.0
Name: mock-services
Version: 0.3.1
Summary: Mock services.
Home-page: https://github.com/novafloss/mock-services
Author: Florent Pigout
Author-email: florent.pigout@novapost.fr
License: MIT
Keywords: http,mock,requests,rest
Platform: UNKNOWN
Classifier: Development Status :: 4 - Beta
Classifier: Environment :: Console
Classifier: Intended Audience :: Developers
Classifier: License :: OSI Approved :: MIT License
Classifier: Programming Language :: Python
Classifier: Programming Language :: Python :: 2
Classifier: Programming Language :: Python :: 2.7
Classifier: Programming Language :: Python :: 3
Classifier: Programming Language :: Python :: 3.4
Classifier: Programming Language :: Python :: 3.5
Classifier: Programming Language :: Python :: 3.6
Provides-Extra: test
Provides-Extra: release
Requires-Dist: attrs
Requires-Dist: funcsigs
Requires-Dist: requests-mock (<=1.1.0)
Provides-Extra: release
Requires-Dist: wheel; extra == 'release'
Requires-Dist: zest.releaser; extra == 'release'
Provides-Extra: test
Requires-Dist: flake8; extra == 'test'
